unit_systems/__init__.py
unit_systems/measurement_system.py
unit_systems/physical_system.py
unit_systems/prefixes.py
unit_systems-1.0.2.dist-info/LICENCE.txt
unit_systems-1.0.2.dist-info/METADATA
unit_systems-1.0.2.dist-info/WHEEL
unit_systems-1.0.2.dist-info/top_level.txt
unit_systems-1.0.2.dist-info/RECORD
