Metadata-Version: 2.1
Name: unit-systems
Version: 1.0.2
Summary: Physical unit_systems in python
Home-page: https://github.com/ndeutschmann/py-units
Author: Nicolas Deutschmann
Author-email: nicolas.deutschmann@gmail.com
License: LICENSE.txt
Platform: UNKNOWN
Classifier: Programming Language :: Python :: 3
Classifier: License :: OSI Approved :: MIT License
Classifier: Operating System :: OS Independent
Requires-Dist: sympy
